[
    {
      "src": "./assets/DSC_0110.JPG",
      "width": 3,
      "height": 2
    },
    {
      "src": "./assets/DSC_0216.JPG",
      "width": 3,
      "height": 2
    },
    {
      "src": "./assets/DSC_0367.JPG",
      "width": 3,
      "height": 2
    },
    {
      "src": "./assets/plate-img.JPG",
      "width": 3,
      "height": 2
    },
    {
      "src": "./assets/rest-img.JPG",
      "width": 3,
      "height": 2
    },
    {
      "src": "./assets/DSC_0025.JPG",
      "width": 3,
      "height": 2
    }
]